-- BYTECODE -- index.lua:0-0
0001    KSTR     3   0
0002    IST          1
0003    JMP      4 => 0005
0004    KSTR     1   1
0005 => ISNES    1   1
0006    JMP      4 => 0012
0007    GGET     4   2
0008    MOV      5   0
0009    CALL     4   2   2
0010    ISNES    4   3
0011    JMP      4 => 0014
0012 => MOV      3   0
0013    JMP      4 => 0019
0014 => UGET     4   0
0015    TGETS    4   4   4
0016    MOV      5   0
0017    CALL     4   2   2
0018    MOV      3   4
0019 => ISNES    1   5
0020    JMP      4 => 0028
0021    GGET     4   6
0022    TGETS    4   4   7
0023    TGETS    4   4   8
0024    KSTR     5   9
0025    KSTR     6  10
0026    CALL     4   1   3
0027    JMP      4 => 0048
0028 => ISNES    1  11
0029    JMP      4 => 0043
0030    IST          2
0031    JMP      4 => 0033
0032    KSTR     2  12
0033 => GGET     4   6
0034    TGETS    4   4   7
0035    TGETS    4   4   8
0036    KSTR     5  13
0037    KSTR     6  14
0038    MOV      7   2
0039    KSTR     8  15
0040    CAT      6   6   8
0041    CALL     4   1   3
0042    JMP      4 => 0048
0043 => GGET     4   6
0044    TGETS    4   4   7
0045    TGETS    4   4  16
0046    KSTR     5  17
0047    CALL     4   1   2
0048 => GGET     4   6
0049    TGETS    4   4   7
0050    TGETS    4   4  18
0051    MOV      5   3
0052    CALL     4   1   2
0053    RET0     0   1

-- BYTECODE -- index.lua:0-0
0001    TNEW     0   3
0002    VARG     1   0   0
0003    TSETM    1   0
0004    KSHORT   1   0
0005    GGET     2   0
0006    MOV      3   0
0007    KPRI     4   0
0008    ISNEXT   5 => 0022
0009 => KSHORT   7   0
0010    GGET     8   1
0011    LEN      8   8
0012    KSHORT   9   1
0013    FORI     7 => 0022
0014 => GGET    11   1
0015    TGETV   11  11  10
0016    ISNEV   11   6
0017    JMP     11 => 0021
0018    KSHORT  11   2
0019    POW     11  11  10
0020    ADDVV    1   1  11
0021 => FORL     7 => 0014
0022 => ITERN    5   3   3
0023    ITERL    5 => 0009
0024    RET1     1   2